wbtasks/__init__.py
wbtasks/admin.py
wbtasks/apps.py
wbtasks/factories.py
wbtasks/filters.py
wbtasks/models.py
wbtasks/serializers.py
wbtasks/tasks.py
wbtasks/urls.py
wbtasks/migrations/0001_initial_squashed_squashed_0006_alter_task_assigned_to_alter_task_in_charge_and_more.py
wbtasks/migrations/__init__.py
wbtasks/tests/__init__.py
wbtasks/tests/conftest.py
wbtasks/tests/test_filters.py
wbtasks/tests/test_models.py
wbtasks/tests/test_serializers.py
wbtasks/tests/test_tasks.py
wbtasks/tests/tests.py
wbtasks/viewsets/__init__.py
wbtasks/viewsets/buttons.py
wbtasks/viewsets/display.py
wbtasks/viewsets/menu.py
wbtasks/viewsets/titles.py
wbtasks/viewsets/viewsets.py
wbtasks-2.2.6.dist-info/METADATA
wbtasks-2.2.6.dist-info/WHEEL
wbtasks-2.2.6.dist-info/RECORD
